flytekitplugins_onnxpytorch-1.16.12-py3.14-nspkg.pth
flytekitplugins/onnxpytorch/__init__.py
flytekitplugins/onnxpytorch/schema.py
flytekitplugins_onnxpytorch-1.16.12.dist-info/METADATA
flytekitplugins_onnxpytorch-1.16.12.dist-info/WHEEL
flytekitplugins_onnxpytorch-1.16.12.dist-info/namespace_packages.txt
flytekitplugins_onnxpytorch-1.16.12.dist-info/top_level.txt
flytekitplugins_onnxpytorch-1.16.12.dist-info/RECORD
